isobiscuit_engine/__engine.py
isobiscuit_engine/__init__.py
isobiscuit_engine/_engine.pyx
isobiscuit_engine/_engine_py.py
isobiscuit_engine/engine.pyi
isobiscuit_engine/_engine.c
isobiscuit_engine/_engine.html
isobiscuit_engine/engine.so
isobiscuit_engine-0.1.21.dist-info/LICENSE
isobiscuit_engine-0.1.21.dist-info/METADATA
isobiscuit_engine-0.1.21.dist-info/WHEEL
isobiscuit_engine-0.1.21.dist-info/RECORD
