Metadata-Version: 2.1
Name: isobiscuit-engine
Version: 0.1.21
Summary: 
Author: trollmii
Author-email: trollmii@outlook.de
Requires-Python: >=3.9,<4.0
Classifier: Programming Language :: Python :: 3
Classifier: Programming Language :: Python :: 3.9
Classifier: Programming Language :: Python :: 3.10
Classifier: Programming Language :: Python :: 3.11
Classifier: Programming Language :: Python :: 3.12
Classifier: Programming Language :: Python :: 3.13
Requires-Dist: colorama (>=0.4.6,<0.5.0)
Requires-Dist: cython (>=0.29.24,<0.30.0)
